setup.py
grasshopper/__init__.py
grasshopper/framework.py
grasshopper_web.egg-info/PKG-INFO
grasshopper_web.egg-info/SOURCES.txt
grasshopper_web.egg-info/dependency_links.txt
grasshopper_web.egg-info/not-zip-safe
grasshopper_web.egg-info/pbr.json
grasshopper_web.egg-info/top_level.txt