Metadata-Version: 1.1
Name: grasshopper-web
Version: 0.1
Summary: The Grasshopper python microframework
Home-page: http://github.com/aholyoke/grasshopper
Author: Alex Holyoke
Author-email: aholyoke@uwaterloo.ca
License: BSD
Platform: UNKNOWN
Classifier: Development Status :: 2 - Pre-Alpha
Classifier: License :: OSI Approved :: BSD License
Classifier: Programming Language :: Python :: 2.7
